repository_mirror/__init__.py
repository_mirror/main.py
repository_mirror/command/__init__.py
repository_mirror/command/config.py
repository_mirror/command/sync.py
repository_mirror/conf/__init__.py
repository_mirror/conf/default_conf.py
repository_mirror/conf/global_conf.py
repository_mirror/conf/my_conf.py
repository_mirror/lib/__init__.py
repository_mirror/lib/output.py
repository_mirror/lib/spaceone_client.py
repository_mirror/manager/__init__.py
repository_mirror/manager/plugin_manager.py
repository_mirror/manager/policy_manager.py
repository_mirror/manager/repository_manager.py
repository_mirror/manager/schema_manager.py
repository_mirror-1.0.2.dist-info/METADATA
repository_mirror-1.0.2.dist-info/WHEEL
repository_mirror-1.0.2.dist-info/entry_points.txt
repository_mirror-1.0.2.dist-info/top_level.txt
repository_mirror-1.0.2.dist-info/RECORD
